ptools_base/__init__.py
ptools_base/schema.py
ptools_base/tool.py
ptools_base-1.1.5.dist-info/METADATA
ptools_base-1.1.5.dist-info/WHEEL
ptools_base-1.1.5.dist-info/top_level.txt
ptools_base-1.1.5.dist-info/RECORD
