Metadata-Version: 2.1
Name: ptools-base
Version: 1.1.5
Summary: P Test Platform Tools Base Lib
Home-page: 
Author: JasonZhang
Author-email: qwertjkl9090@163.com
Classifier: License :: OSI Approved :: MIT License
Classifier: Intended Audience :: Developers
Classifier: Operating System :: OS Independent
Classifier: Programming Language :: Python :: 3.12
Requires-Dist: pydantic ==2.11.7
